sprinkler_util/__init__.py
sprinkler_util/py.typed
sprinkler_util/sprinkler_util.py
sprinkler_util-0.1.3.dist-info/METADATA
sprinkler_util-0.1.3.dist-info/WHEEL
sprinkler_util-0.1.3.dist-info/top_level.txt
sprinkler_util-0.1.3.dist-info/RECORD
