Metadata-Version: 2.1
Name: sprinkler_util
Version: 0.1.3
Summary: sprinkler_util
Home-page: https://github.com/henryivesjones/sprinkler/sprinkler_util/python
Author: Henry Jones
Author-email: Henry Jones <henryivesjones@gmail.com>
License: GPL-3.0-or-later
Keywords: sprinkler
Classifier: License :: OSI Approved :: GNU General Public License v3 or later (GPLv3+)
Classifier: Programming Language :: Python :: 3
Classifier: Programming Language :: Python :: 3.7
Classifier: Programming Language :: Python :: 3.8
Classifier: Programming Language :: Python :: 3.9
Classifier: Programming Language :: Python :: 3.10
Classifier: Programming Language :: Python :: 3.11
Requires-Python: >=3.6
